crosstalk/__init__.py
crosstalk/crosstalk.py
crosstalk-0.1.0.dist-info/METADATA
crosstalk-0.1.0.dist-info/WHEEL
crosstalk-0.1.0.dist-info/entry_points.txt
crosstalk-0.1.0.dist-info/top_level.txt
crosstalk-0.1.0.dist-info/RECORD
